[
    {
        "username": "Ethel",
        "firstname": "Ethel",
        "lastName": "Price",
        "gender": "female",
        "company": "Johnson, Johnson and Partners, LLC CMP DDC",
        "age": 22,
        "email": "user@example.com"
    },
    {
        "username": "Claudine",
        "firstname": "Claudine",
        "lastName": "Neal",
        "gender": "female",
        "company": "Sealoud",
        "age": 55,
        "email": "user@example.com"
    },
    {
        "username": "Beryl",
        "firstname": "Beryl",
        "lastName": "Rice",
        "gender": "female",
        "company": "Velity",
        "age": 67,
        "email": "user@example.com"
    },
    {
        "username": "Wilder",
        "firstname": "Wilder",
        "lastName": "Gonzales",
        "gender": "male",
        "company": "Geekko",
        "email": "user@example.com"
    },
    {
        "username": "Georgina",
        "firstname": "Georgina",
        "lastName": "Schultz",
        "gender": "female",
        "company": "Suretech",
        "email": "user@example.com"
    },
    {
        "username": "Carroll",
        "firstname": "Carroll",
        "lastName": "Buchanan",
        "gender": "male",
        "company": "Ecosys",
        "email": "user@example.com"
    },
    {
        "username": "Valarie",
        "firstname": "Valarie",
        "lastName": "Atkinson",
        "gender": "female",
        "company": "Hopeli",
        "email": "user@example.com"
    },
    {
        "username": "Schroeder",
        "firstname": "Schroeder",
        "lastName": "Mathews",
        "gender": "male",
        "company": "Polarium",
        "email": "user@example.com"
    },
    {
        "username": "Lynda",
        "firstname": "Lynda",
        "lastName": "Mendoza",
        "gender": "female",
        "company": "Dogspa",
        "email": "user@example.com"
    },
    {
        "username": "Sarah",
        "firstname": "Sarah",
        "lastName": "Massey",
        "gender": "female",
        "company": "Bisba",
        "email": "user@example.com"
    },
    {
        "username": "Robles",
        "firstname": "Robles",
        "lastName": "Boyle",
        "gender": "male",
        "company": "Comtract",
        "email": "user@example.com"
    },
    {
        "username": "Evans",
        "firstname": "Evans",
        "lastName": "Hickman",
        "gender": "male",
        "company": "Parleynet",
        "email": "user@example.com"
    },
    {
        "username": "Dawson",
        "firstname": "Dawson",
        "lastName": "Barber",
        "gender": "male",
        "company": "Dymi",
        "email": "user@example.com"
    },
    {
        "username": "Bruce",
        "firstname": "Bruce",
        "lastName": "Strong",
        "gender": "male",
        "company": "Xyqag",
        "email": "user@example.com"
    },
    {
        "username": "Nellie",
        "firstname": "Nellie",
        "lastName": "Whitfield",
        "gender": "female",
        "company": "Exospace",
        "email": "user@example.com"
    },
    {
        "username": "Jackson",
        "firstname": "Jackson",
        "lastName": "Macias",
        "gender": "male",
        "company": "Aquamate",
        "email": "user@example.com"
    },
    {
        "username": "Pena",
        "firstname": "Pena",
        "lastName": "Pena",
        "gender": "male",
        "company": "Quarx",
        "email": "user@example.com"
    },
    {
        "username": "Lelia",
        "firstname": "Lelia",
        "lastName": "Gates",
        "gender": "female",
        "company": "Proxsoft",
        "email": "user@example.com"
    },
    {
        "username": "Letitia",
        "firstname": "Letitia",
        "lastName": "Vasquez",
        "gender": "female",
        "company": "Slumberia",
        "email": "user@example.com"
    },
    {
        "username": "Trevino",
        "firstname": "Trevino",
        "lastName": "Moreno",
        "gender": "male",
        "company": "Conjurica",
        "email": "user@example.com"
    },
    {
        "username": "Barr",
        "firstname": "Barr",
        "lastName": "Page",
        "gender": "male",
        "company": "Apex",
        "email": "user@example.com"
    },
    {
        "username": "Kirkland",
        "firstname": "Kirkland",
        "lastName": "Merrill",
        "gender": "male",
        "company": "Utara",
        "email": "user@example.com"
    },
    {
        "username": "Blanche",
        "firstname": "Blanche",
        "lastName": "Conley",
        "gender": "female",
        "company": "Imkan",
        "email": "user@example.com"
    },
    {
        "username": "Atkins",
        "firstname": "Atkins",
        "lastName": "Dunlap",
        "gender": "male",
        "company": "Comveyor",
        "email": "user@example.com"
    },
    {
        "username": "Everett",
        "firstname": "Everett",
        "lastName": "Foreman",
        "gender": "male",
        "company": "Maineland",
        "email": "user@example.com"
    },
    {
        "username": "Gould",
        "firstname": "Gould",
        "lastName": "Randolph",
        "gender": "male",
        "company": "Intergeek",
        "email": "user@example.com"
    },
    {
        "username": "Kelli",
        "firstname": "Kelli",
        "lastName": "Leon",
        "gender": "female",
        "company": "Verbus",
        "email": "user@example.com"
    },
    {
        "username": "Freda",
        "firstname": "Freda",
        "lastName": "Mason",
        "gender": "female",
        "company": "Accidency",
        "email": "user@example.com"
    },
    {
        "username": "Tucker",
        "firstname": "Tucker",
        "lastName": "Maxwell",
        "gender": "male",
        "company": "Lumbrex",
        "email": "user@example.com"
    },
    {
        "username": "Yvonne",
        "firstname": "Yvonne",
        "lastName": "Parsons",
        "gender": "female",
        "company": "Zolar",
        "email": "user@example.com"
    },
    {
        "username": "Woods",
        "firstname": "Woods",
        "lastName": "Key",
        "gender": "male",
        "company": "Bedder",
        "email": "user@example.com"
    },
    {
        "username": "Stephens",
        "firstname": "Stephens",
        "lastName": "Reilly",
        "gender": "male",
        "company": "Acusage",
        "email": "user@example.com"
    },
    {
        "username": "Mcfarland",
        "firstname": "Mcfarland",
        "lastName": "Sparks",
        "gender": "male",
        "company": "Comvey",
        "email": "user@example.com"
    },
    {
        "username": "Jocelyn",
        "firstname": "Jocelyn",
        "lastName": "Sawyer",
        "gender": "female",
        "company": "Fortean",
        "email": "user@example.com"
    },
    {
        "username": "Renee",
        "firstname": "Renee",
        "lastName": "Barr",
        "gender": "female",
        "company": "Kiggle",
        "email": "user@example.com"
    },
    {
        "username": "Gaines",
        "firstname": "Gaines",
        "lastName": "Beck",
        "gender": "male",
        "company": "Sequitur",
        "email": "user@example.com"
    },
    {
        "username": "Luisa",
        "firstname": "Luisa",
        "lastName": "Farrell",
        "gender": "female",
        "company": "Cinesanct",
        "email": "user@example.com"
    },
    {
        "username": "Robyn",
        "firstname": "Robyn",
        "lastName": "Strickland",
        "gender": "female",
        "company": "Obones",
        "email": "user@example.com"
    },
    {
        "username": "Roseann",
        "firstname": "Roseann",
        "lastName": "Jarvis",
        "gender": "female",
        "company": "Aquazure",
        "email": "user@example.com"
    },
    {
        "username": "Johnston",
        "firstname": "Johnston",
        "lastName": "Park",
        "gender": "male",
        "company": "Netur",
        "email": "user@example.com"
    },
    {
        "username": "Wong",
        "firstname": "Wong",
        "lastName": "Craft",
        "gender": "male",
        "company": "Opticall",
        "email": "user@example.com"
    },
    {
        "username": "Merritt",
        "firstname": "Merritt",
        "lastName": "Cole",
        "gender": "male",
        "company": "Techtrix",
        "email": "user@example.com"
    },
    {
        "username": "Dale",
        "firstname": "Dale",
        "lastName": "Byrd",
        "gender": "female",
        "company": "Kneedles",
        "email": "user@example.com"
    },
    {
        "username": "Sara",
        "firstname": "Sara",
        "lastName": "Delgado",
        "gender": "female",
        "company": "Netagy",
        "email": "user@example.com"
    },
    {
        "username": "Alisha",
        "firstname": "Alisha",
        "lastName": "Myers",
        "gender": "female",
        "company": "Intradisk",
        "email": "user@example.com"
    },
    {
        "username": "Felecia",
        "firstname": "Felecia",
        "lastName": "Smith",
        "gender": "female",
        "company": "Futurity",
        "email": "user@example.com"
    },
    {
        "username": "Neal",
        "firstname": "Neal",
        "lastName": "Harvey",
        "gender": "male",
        "company": "Pyramax",
        "email": "user@example.com"
    },
    {
        "username": "Nola",
        "firstname": "Nola",
        "lastName": "Miles",
        "gender": "female",
        "company": "Sonique",
        "email": "user@example.com"
    },
    {
        "username": "Herring",
        "firstname": "Herring",
        "lastName": "Pierce",
        "gender": "male",
        "company": "Geeketron",
        "email": "user@example.com"
    },
    {
        "username": "Shelley",
        "firstname": "Shelley",
        "lastName": "Rodriquez",
        "gender": "female",
        "company": "Bostonic",
        "email": "user@example.com"
    },
    {
        "username": "Cora",
        "firstname": "Cora",
        "lastName": "Chase",
        "gender": "female",
        "company": "Isonus",
        "email": "user@example.com"
    },
    {
        "username": "Mckay",
        "firstname": "Mckay",
        "lastName": "Santos",
        "gender": "male",
        "company": "Amtas",
        "email": "user@example.com"
    },
    {
        "username": "Hilda",
        "firstname": "Hilda",
        "lastName": "Crane",
        "gender": "female",
        "company": "Jumpstack",
        "email": "user@example.com"
    },
    {
        "username": "Jeanne",
        "firstname": "Jeanne",
        "lastName": "Lindsay",
        "gender": "female",
        "company": "Genesynk",
        "email": "user@example.com"
    },
    {
        "username": "Frye",
        "firstname": "Frye",
        "lastName": "Sharpe",
        "gender": "male",
        "company": "Eplode",
        "email": "user@example.com"
    },
    {
        "username": "Velma",
        "firstname": "Velma",
        "lastName": "Fry",
        "gender": "female",
        "company": "Ronelon",
        "email": "user@example.com"
    },
    {
        "username": "Reyna",
        "firstname": "Reyna",
        "lastName": "Espinoza",
        "gender": "female",
        "company": "Prismatic",
        "email": "user@example.com"
    },
    {
        "username": "Spencer",
        "firstname": "Spencer",
        "lastName": "Sloan",
        "gender": "male",
        "company": "Comverges",
        "email": "user@example.com"
    },
    {
        "username": "Graham",
        "firstname": "Graham",
        "lastName": "Marsh",
        "gender": "male",
        "company": "Medifax",
        "email": "user@example.com"
    },
    {
        "username": "Hale",
        "firstname": "Hale",
        "lastName": "Boone",
        "gender": "male",
        "company": "Digial",
        "email": "user@example.com"
    },
    {
        "username": "Wiley",
        "firstname": "Wiley",
        "lastName": "Hubbard",
        "gender": "male",
        "company": "Zensus",
        "email": "user@example.com"
    },
    {
        "username": "Blackburn",
        "firstname": "Blackburn",
        "lastName": "Drake",
        "gender": "male",
        "company": "Frenex",
        "email": "user@example.com"
    },
    {
        "username": "Franco",
        "firstname": "Franco",
        "lastName": "Hunter",
        "gender": "male",
        "company": "Rockabye",
        "email": "user@example.com"
    },
    {
        "username": "Barnett",
        "firstname": "Barnett",
        "lastName": "Case",
        "gender": "male",
        "company": "Norali",
        "email": "user@example.com"
    },
    {
        "username": "Alexander",
        "firstname": "Alexander",
        "lastName": "Foley",
        "gender": "male",
        "company": "Geekosis",
        "email": "user@example.com"
    },
    {
        "username": "Lynette",
        "firstname": "Lynette",
        "lastName": "Stein",
        "gender": "female",
        "company": "Macronaut",
        "email": "user@example.com"
    },
    {
        "username": "Anthony",
        "firstname": "Anthony",
        "lastName": "Joyner",
        "gender": "male",
        "company": "Senmei",
        "email": "user@example.com"
    },
    {
        "username": "Garrett",
        "firstname": "Garrett",
        "lastName": "Brennan",
        "gender": "male",
        "company": "Bluegrain",
        "email": "user@example.com"
    },
    {
        "username": "Betsy",
        "firstname": "Betsy",
        "lastName": "Horton",
        "gender": "female",
        "company": "Zilla",
        "email": "user@example.com"
    },
    {
        "username": "Patton",
        "firstname": "Patton",
        "lastName": "Small",
        "gender": "male",
        "company": "Genmex",
        "email": "user@example.com"
    },
    {
        "username": "Lakisha",
        "firstname": "Lakisha",
        "lastName": "Huber",
        "gender": "female",
        "company": "Insource",
        "email": "user@example.com"
    },
    {
        "username": "Lindsay",
        "firstname": "Lindsay",
        "lastName": "Avery",
        "gender": "female",
        "company": "Unq",
        "email": "user@example.com"
    },
    {
        "username": "Ayers",
        "firstname": "Ayers",
        "lastName": "Hood",
        "gender": "male",
        "company": "Accuprint",
        "email": "user@example.com"
    },
    {
        "username": "Torres",
        "firstname": "Torres",
        "lastName": "Durham",
        "gender": "male",
        "company": "Uplinx",
        "email": "user@example.com"
    },
    {
        "username": "Vincent",
        "firstname": "Vincent",
        "lastName": "Hernandez",
        "gender": "male",
        "company": "Talendula",
        "email": "user@example.com"
    },
    {
        "username": "Baird",
        "firstname": "Baird",
        "lastName": "Ryan",
        "gender": "male",
        "company": "Aquasseur",
        "email": "user@example.com"
    },
    {
        "username": "Georgia",
        "firstname": "Georgia",
        "lastName": "Mercer",
        "gender": "female",
        "company": "Skyplex",
        "email": "user@example.com"
    },
    {
        "username": "Francesca",
        "firstname": "Francesca",
        "lastName": "Elliott",
        "gender": "female",
        "company": "Nspire",
        "email": "user@example.com"
    },
    {
        "username": "Lyons",
        "firstname": "Lyons",
        "lastName": "Peters",
        "gender": "male",
        "company": "Quinex",
        "email": "user@example.com"
    },
    {
        "username": "Kristi",
        "firstname": "Kristi",
        "lastName": "Brewer",
        "gender": "female",
        "company": "Oronoko",
        "email": "user@example.com"
    },
    {
        "username": "Tonya",
        "firstname": "Tonya",
        "lastName": "Bray",
        "gender": "female",
        "company": "Insuron",
        "email": "user@example.com"
    },
    {
        "username": "Valenzuela",
        "firstname": "Valenzuela",
        "lastName": "Huff",
        "gender": "male",
        "company": "Applideck",
        "email": "user@example.com"
    },
    {
        "username": "Tiffany",
        "firstname": "Tiffany",
        "lastName": "Anderson",
        "gender": "female",
        "company": "Zanymax",
        "email": "user@example.com"
    },
    {
        "username": "Jerri",
        "firstname": "Jerri",
        "lastName": "King",
        "gender": "female",
        "company": "Eventex",
        "email": "user@example.com"
    },
    {
        "username": "Rocha",
        "firstname": "Rocha",
        "lastName": "Meadows",
        "gender": "male",
        "company": "Goko",
        "email": "user@example.com"
    },
    {
        "username": "Marcy",
        "firstname": "Marcy",
        "lastName": "Green",
        "gender": "female",
        "company": "Pharmex",
        "email": "user@example.com"
    },
    {
        "username": "Kirk",
        "firstname": "Kirk",
        "lastName": "Cross",
        "gender": "male",
        "company": "Portico",
        "email": "user@example.com"
    },
    {
        "username": "Hattie",
        "firstname": "Hattie",
        "lastName": "Mullen",
        "gender": "female",
        "company": "Zilencio",
        "email": "user@example.com"
    },
    {
        "username": "Deann",
        "firstname": "Deann",
        "lastName": "Bridges",
        "gender": "female",
        "company": "Equitox",
        "email": "user@example.com"
    },
    {
        "username": "Chaney",
        "firstname": "Chaney",
        "lastName": "Roach",
        "gender": "male",
        "company": "Qualitern",
        "email": "user@example.com"
    },
    {
        "username": "Consuelo",
        "firstname": "Consuelo",
        "lastName": "Dickson",
        "gender": "female",
        "company": "Poshome",
        "email": "user@example.com"
    },
    {
        "username": "Billie",
        "firstname": "Billie",
        "lastName": "Rowe",
        "gender": "female",
        "company": "Cemention",
        "email": "user@example.com"
    },
    {
        "username": "Bean",
        "firstname": "Bean",
        "lastName": "Donovan",
        "gender": "male",
        "company": "Mantro",
        "email": "user@example.com"
    },
    {
        "username": "Lancaster",
        "firstname": "Lancaster",
        "lastName": "Patel",
        "gender": "male",
        "company": "Krog",
        "email": "user@example.com"
    },
    {
        "username": "Rosa",
        "firstname": "Rosa",
        "lastName": "Dyer",
        "gender": "female",
        "company": "Netility",
        "email": "user@example.com"
    },
    {
        "username": "Christine",
        "firstname": "Christine",
        "lastName": "Compton",
        "gender": "female",
        "company": "Bleeko",
        "email": "user@example.com"
    },
    {
        "username": "Milagros",
        "firstname": "Milagros",
        "lastName": "Finch",
        "gender": "female",
        "company": "Handshake",
        "email": "user@example.com"
    },
    {
        "username": "Ericka",
        "firstname": "Ericka",
        "lastName": "Alvarado",
        "gender": "female",
        "company": "Lyrichord",
        "email": "user@example.com"
    },
    {
        "username": "Sylvia",
        "firstname": "Sylvia",
        "lastName": "Sosa",
        "gender": "female",
        "company": "Circum",
        "email": "user@example.com"
    },
    {
        "username": "Humphrey",
        "firstname": "Humphrey",
        "lastName": "Curtis",
        "gender": "male",
        "company": "Corepan",
        "email": "user@example.com"
    }
]